README.md
setup.py
anel_pwrctrl/__init__.py
anel_pwrctrl_homeassistant.egg-info/PKG-INFO
anel_pwrctrl_homeassistant.egg-info/SOURCES.txt
anel_pwrctrl_homeassistant.egg-info/dependency_links.txt
anel_pwrctrl_homeassistant.egg-info/top_level.txt