Metadata-Version: 1.0
Name: anel-pwrctrl-homeassistant
Version: 0.0.1.dev2
Summary: Discover and control ANEL NET-PwrCtrl devices.
Home-page: UNKNOWN
Author: Martin Weinelt
Author-email: martin@linuxlounge.net
License: MIT
Platform: UNKNOWN
